[{"anonymous":false,"inputs":[{"indexed":true,"internalType":"address","name":"receiver","type":"address"},{"indexed":false,"internalType":"uint256","name":"amount","type":"uint256"}],"name":"DepositProcessed","type":"event"},{"anonymous":false,"inputs":[{"indexed":true,"internalType":"address","name":"tokenL1","type":"address"},{"indexed":true,"internalType":"address","name":"tokenL2","type":"address"},{"indexed":true,"internalType":"address","name":"receiver","type":"address"},{"indexed":false,"internalType":"uint256","name":"amount","type":"uint256"}],"name":"ERC20DepositProcessed","type":"event"},{"anonymous":false,"inputs":[{"indexed":true,"internalType":"address","name":"tokenL1","type":"address"},{"indexed":true,"internalType":"address","name":"tokenL2","type":"address"},{"indexed":true,"internalType":"address","name":"receiverOnL1","type":"address"},{"indexed":false,"internalType":"uint256","name":"amount","type":"uint256"}],"name":"ERC20WithdrawalInitiated","type":"event"},{"anonymous":false,"inputs":[{"indexed":true,"internalType":"address","name":"senderOnL2","type":"address"},{"indexed":true,"internalType":"address","name":"receiverOnL1","type":"address"},{"indexed":true,"internalType":"uint256","name":"amount","type":"uint256"}],"name":"WithdrawalInitiated","type":"event"},{"inputs":[],"name":"BURN_ADDRESS","outputs":[{"internalType":"address","name":"","type":"address"}],"stateMutability":"view","type":"function"},{"inputs":[],"name":"ETH_TOKEN","outputs":[{"internalType":"address","name":"","type":"address"}],"stateMutability":"view","type":"function"},{"inputs":[],"name":"L1_MESSENGER","outputs":[{"internalType":"address","name":"","type":"address"}],"stateMutability":"view","type":"function"},{"inputs":[{"internalType":"address","name":"tokenL1","type":"address"},{"internalType":"address","name":"tokenL2","type":"address"},{"internalType":"address","name":"destination","type":"address"},{"internalType":"uint256","name":"amount","type":"uint256"}],"name":"mintERC20","outputs":[],"stateMutability":"nonpayable","type":"function"},{"inputs":[{"internalType":"address","name":"to","type":"address"}],"name":"mintETH","outputs":[],"stateMutability":"payable","type":"function"},{"inputs":[{"internalType":"address","name":"tokenL1","type":"address"},{"internalType":"address","name":"tokenL2","type":"address"},{"internalType":"address","name":"destination","type":"address"},{"internalType":"uint256","name":"amount","type":"uint256"}],"name":"tryMintERC20","outputs":[],"stateMutability":"nonpayable","type":"function"},{"inputs":[{"internalType":"address","name":"_receiverOnL1","type":"address"}],"name":"withdraw","outputs":[],"stateMutability":"payable","type":"function"},{"inputs":[{"internalType":"address","name":"tokenL1","type":"address"},{"internalType":"address","name":"tokenL2","type":"address"},{"internalType":"address","name":"destination","type":"address"},{"internalType":"uint256","name":"amount","type":"uint256"}],"name":"withdrawERC20","outputs":[],"stateMutability":"nonpayable","type":"function"}]